MANIFEST.in
requirements.txt
setup.py
molbiox/VERSION
molbiox/__init__.py
molbiox/settings.py
molbiox.egg-info/PKG-INFO
molbiox.egg-info/SOURCES.txt
molbiox.egg-info/dependency_links.txt
molbiox.egg-info/entry_points.txt
molbiox.egg-info/not-zip-safe
molbiox.egg-info/requires.txt
molbiox.egg-info/top_level.txt
molbiox/algor/__init__.py
molbiox/algor/aligner.py
molbiox/algor/arrows.py
molbiox/algor/interval.py
molbiox/algor/mapping.py
molbiox/algor/mapping2.py
molbiox/algor/mutate.py
molbiox/algor/relational.py
molbiox/algor/statis.py
molbiox/algor/transcode.py
molbiox/algor/translate.py
molbiox/algor/traverse.py
molbiox/execute/__init__.py
molbiox/execute/concatenate.py
molbiox/execute/generate.py
molbiox/execute/primer.py
molbiox/execute/project.py
molbiox/execute/randseq.py
molbiox/execute/relational.py
molbiox/execute/relational_.py
molbiox/execute/revcompl.py
molbiox/execute/select.py
molbiox/execute/seqinfo.py
molbiox/execute/set_operators.py
molbiox/execute/translate.py
molbiox/execute/visualize.py
molbiox/execute/zzxp.py
molbiox/frame/__init__.py
molbiox/frame/command.py
molbiox/frame/compat.py
molbiox/frame/containers.py
molbiox/frame/interactive.py
molbiox/frame/locate.py
molbiox/frame/regexon.py
molbiox/frame/signature.py
molbiox/frame/streaming.py
molbiox/frame/testing.py
molbiox/io/__init__.py
molbiox/io/arrows.py
molbiox/io/blast.py
molbiox/io/fasta.py
molbiox/io/fastq.py
molbiox/io/genbank.py
molbiox/io/glimmer.py
molbiox/io/hmmscan.py
molbiox/io/primer.py
molbiox/io/report.py
molbiox/io/sambam.py
molbiox/io/submat.py
molbiox/io/tabular.py
molbiox/io/tmhmm.py
molbiox/io/uniprot.py
molbiox/kb/__init__.py
molbiox/kb/blast.py
molbiox/kb/constants.py
molbiox/kb/proteins.py
molbiox/kb/transcode.py
molbiox/kb/translate.py
molbiox/lib/__init__.py
molbiox/lib/align.c
molbiox/templates/__init__.py
molbiox/templates/__init__.pyc
molbiox/templates/d.arrows.table.html
molbiox/templates/d.arrows.xml
molbiox/templates/d.feat-create.sql
molbiox/templates/d.feat-insert-glimmer3.sql
molbiox/templates/d.feat-update-blastT.sql
molbiox/templates/d.feat-update-gc.sql
molbiox/templates/d.feat-update-pfamT.sql
molbiox/templates/d.genbank.tpl
molbiox/templates/d.primer3.txt
