Metadata-Version: 1.1
Name: molbiox
Version: 0.0.12
Summary: utilities for bioinformatics
Home-page: https://github.com/frozflame/molbiox
Author: frozflame
Author-email: lendoli@163.com
License: GNU General Public License (GPL)
Keywords: bioinformatics
Platform: UNKNOWN
Classifier: Topic :: Scientific/Engineering
Classifier: Topic :: Scientific/Engineering :: Bio-Informatics
Classifier: Programming Language :: Python :: 2
Classifier: Programming Language :: Python :: 3
